redisworks/__init__.py
redisworks/helper.py
redisworks/redisworks.py
redisworks-0.4.0.dist-info/AUTHORS
redisworks-0.4.0.dist-info/LICENSE
redisworks-0.4.0.dist-info/METADATA
redisworks-0.4.0.dist-info/WHEEL
redisworks-0.4.0.dist-info/top_level.txt
redisworks-0.4.0.dist-info/RECORD
