Metadata-Version: 2.1
Name: redisworks
Version: 0.4.0
Summary: Pythonic Redis Client.
Home-page: https://github.com/seperman/redisworks
Download-URL: https://github.com/seperman/redisworks/tarball/master
Author: Seperman
Author-email: sep@zepworks.com
License: MIT
Classifier: Intended Audience :: Developers
Classifier: Operating System :: OS Independent
Classifier: Topic :: Software Development
Classifier: Programming Language :: Python :: 3.7
Classifier: Programming Language :: Python :: 3.8
Classifier: Programming Language :: Python :: 3.9
Classifier: Programming Language :: Python :: 3.10
Classifier: Programming Language :: Python :: 3.11
Classifier: Programming Language :: Python :: Implementation :: PyPy
Classifier: Development Status :: 5 - Production/Stable
Classifier: License :: OSI Approved :: MIT License
License-File: LICENSE
License-File: AUTHORS
Requires-Dist: dotobject (>=1.3.1)
Requires-Dist: redis (>=4.3.4)
